[
    {
        "id" : 1,
        "marca" : "Olmo",
        "modelo" : "Regal",
        "rodado" : 29,
        "anio" : 2022,
        "color": "roja",
        "peso" : 16,
        "tipo" : "Montañera",
        "precio" : 120000,
        "vendida" : "si"
    },
    
    {
        "id" : 2,
        "marca" : "Giant",
        "modelo" : "Anthem",
        "rodado" : 29,
        "anio" : 2021,
        "color": "roja",
        "peso" : 16,
        "tipo" : "Montañera",
        "precio" : 120000,
        "vendida" : "si"
    },
    {
        "id" : 3,
        "marca" : "Specialized",
        "modelo" : "Enduro",
        "rodado" : 27.5,
        "anio" : 2019,
        "color": "roja",
        "peso" : 16,
        "tipo" : "Montañera",
        "precio" : 120000,
        "vendida" : "si"
    }
]